pcr_strainer/__init__.py
pcr_strainer/pcr_strainer_v_0_2_4.py
pcr_strainer-0.2.4.dist-info/LICENSE
pcr_strainer-0.2.4.dist-info/METADATA
pcr_strainer-0.2.4.dist-info/WHEEL
pcr_strainer-0.2.4.dist-info/entry_points.txt
pcr_strainer-0.2.4.dist-info/top_level.txt
pcr_strainer-0.2.4.dist-info/RECORD
