Metadata-Version: 2.1
Name: pcr-strainer
Version: 0.2.4
Summary: A tool for assessing the inclusivity of PCR oligos for diagnostic assays and amplicon sequencing schemes
Home-page: https://github.com/KevinKuchinski/PCR_strainer
Author: Kevin Kuchinski
Author-email: kevin.kuchinski@bccdc.ca
License: UNKNOWN
Project-URL: Bug Tracker, https://github.com/KevinKuchinski/PCR_strainer/issues
Platform: UNKNOWN
Classifier: Programming Language :: Python :: 3
Classifier: License :: OSI Approved :: MIT License
Classifier: Operating System :: OS Independent
Requires-Python: >=3.7
License-File: LICENSE
